ueli_calculation/Divide3.py
ueli_calculation/GeneralCalculation.py
ueli_calculation/Multiply3.py
ueli_calculation/__init__.py
ueli_calculation-0.1.dist-info/METADATA
ueli_calculation-0.1.dist-info/WHEEL
ueli_calculation-0.1.dist-info/top_level.txt
ueli_calculation-0.1.dist-info/RECORD
