Metadata-Version: 2.1
Name: ueli-calculation
Version: 0.1
Summary: My package in pypi
Home-page: UNKNOWN
Author: Eliane Netto
Author-email: elianenetto82@gmail.com
License: UNKNOWN
Platform: UNKNOWN
